data/db/schema.sql
docs/images/example_map_censo_pt.png
docs/images/example_map_elections_cl.png
prompt2map/__init__.py
prompt2map/types.py
prompt2map/application/core/prompt2map.py
prompt2map/application/generators/openai_map_generator.py
prompt2map/application/maps/bar_chart_map.py
prompt2map/application/maps/choropleth_map.py
prompt2map/application/maps/folium.py
prompt2map/application/prompt2sql/llm_prompt2sql.py
prompt2map/application/prompt2sql/sql_query_processor.py
prompt2map/application/prompt2sql/utils.py
prompt2map/application/retrievers/sql_geo_retriever.py
prompt2map/interfaces/core/geo_retriever.py
prompt2map/interfaces/core/map_generator.py
prompt2map/interfaces/nlp/embedding.py
prompt2map/interfaces/nlp/llm.py
prompt2map/interfaces/sql/geo_database.py
prompt2map/interfaces/sql/prompt2sql.py
prompt2map/providers/geoduckdb.py
prompt2map/providers/openai.py
prompt2map/providers/postgres_db.py
test/test_geoduckdb.py
test/test_prompt2map_api.py
prompt2map-0.1.3.dist-info/LICENSE
prompt2map-0.1.3.dist-info/METADATA
prompt2map-0.1.3.dist-info/WHEEL
prompt2map-0.1.3.dist-info/top_level.txt
prompt2map-0.1.3.dist-info/RECORD
