Metadata-Version: 2.1
Name: prompt2map
Version: 0.1.3
Summary: Dynamic maps generation based on natural language prompts using Retrieval-Augmented Generation (RAG)
Author-email: José Miguel Cordero Carvacho <josemcorderoc@gmail.com>
Maintainer-email: José Miguel Cordero Carvacho <josemcorderoc@gmail.com>
License: MIT License
Project-URL: Repository, https://github.com/josemcorderoc/prompt2map
Keywords: maps,mapping,cartography,gis,webgis,geospatial,llm,nlp,prompt
Classifier: Development Status :: 2 - Pre-Alpha
Classifier: Intended Audience :: Science/Research
Classifier: Topic :: Scientific/Engineering :: GIS
Classifier: License :: OSI Approved :: MIT License
Classifier: Programming Language :: Python :: 3
Classifier: Programming Language :: Python :: 3.10
Classifier: Programming Language :: Python :: 3.11
Classifier: Programming Language :: Python :: 3.12
Classifier: Operating System :: OS Independent
Requires-Python: >=3.10
License-File: LICENSE
Requires-Dist: bidict~=0.23
Requires-Dist: click~=8.1
Requires-Dist: folium~=0.17
Requires-Dist: geopandas~=1.0
Requires-Dist: jsonlines~=4.0
Requires-Dist: matplotlib~=3.9
Requires-Dist: pandas~=2.2
Requires-Dist: plotly~=5.23
Requires-Dist: psycopg~=3.2
Requires-Dist: Shapely~=2.0
Requires-Dist: SQLAlchemy~=2.0
Requires-Dist: sqlglot~=25.8
Requires-Dist: sqlparse~=0.5
Requires-Dist: openai~=1.38
Requires-Dist: mapclassify~=2.8
Requires-Dist: duckdb~=1.1
Requires-Dist: typing-extensions~=4.12
Requires-Dist: pyarrow~=17.0
Provides-Extra: test
Requires-Dist: pytest~=8.3; extra == "test"
Requires-Dist: pytest-mock~=3.14; extra == "test"
Requires-Dist: flake8~=7.1; extra == "test"
